englog/__init__.py
englog/cli.py
englog/py.typed
englog/commands/__init__.py
englog/commands/entry.py
englog/commands/note.py
englog/commands/scratch.py
englog/commands/til.py
englog/commands/time.py
englog/commands/todo.py
englog/core/__init__.py
englog/core/config.py
englog/core/file.py
englog/core/tags.py
englog/core/timer.py
englog/core/todo.py
englog/utils/__init__.py
englog/utils/formatting.py
englog-0.1.0.dist-info/METADATA
englog-0.1.0.dist-info/WHEEL
englog-0.1.0.dist-info/entry_points.txt
englog-0.1.0.dist-info/licenses/LICENSE
englog-0.1.0.dist-info/RECORD
