Metadata-Version: 2.4
Name: englog
Version: 0.1.0
Summary: Minimalist CLI for engineering workdays. Capture time tracking, todos, TILs, and notes as timestamped markdown.
Author-email: Julien Mailleret <8582351+jmlrt@users.noreply.github.com>
License-File: LICENSE
Requires-Python: >=3.12
Requires-Dist: typer>=0.21.0
